{
  "276355": [
    [
      1, 
      33
    ]
  ], 
  "276318": [
    [
      3, 
      349
    ], 
    [
      427, 
      570
    ]
  ], 
  "276458": [
    [
      1, 
      350
    ], 
    [
      352, 
      352
    ]
  ], 
  "276587": [
    [
      1, 
      640
    ], 
    [
      808, 
      1016
    ]
  ], 
  "276581": [
    [
      1, 
      221
    ], 
    [
      248, 
      357
    ], 
    [
      387, 
      415
    ]
  ], 
  "276582": [
    [
      1, 
      125
    ], 
    [
      158, 
      790
    ], 
    [
      834, 
      871
    ]
  ], 
  "276437": [
    [
      164, 
      189
    ], 
    [
      472, 
      758
    ], 
    [
      794, 
      829
    ], 
    [
      866, 
      976
    ], 
    [
      1054, 
      2069
    ], 
    [
      2179, 
      2191
    ]
  ], 
  "276542": [
    [
      1, 
      271
    ], 
    [
      300, 
      503
    ], 
    [
      535, 
      857
    ]
  ], 
  "276543": [
    [
      1, 
      36
    ], 
    [
      74, 
      606
    ], 
    [
      643, 
      952
    ]
  ], 
  "276544": [
    [
      2, 
      105
    ], 
    [
      159, 
      161
    ]
  ], 
  "276586": [
    [
      2, 
      659
    ], 
    [
      665, 
      666
    ], 
    [
      668, 
      668
    ], 
    [
      670, 
      670
    ], 
    [
      672, 
      773
    ]
  ], 
  "276317": [
    [
      3, 
      138
    ]
  ], 
  "276808": [
    [
      28, 
      170
    ], 
    [
      201, 
      230
    ], 
    [
      261, 
      386
    ], 
    [
      420, 
      663
    ], 
    [
      701, 
      815
    ], 
    [
      855, 
      875
    ]
  ], 
  "276807": [
    [
      1, 
      133
    ], 
    [
      160, 
      220
    ]
  ], 
  "276585": [
    [
      1, 
      238
    ], 
    [
      241, 
      242
    ], 
    [
      245, 
      246
    ]
  ], 
  "276384": [
    [
      2, 
      66
    ], 
    [
      133, 
      268
    ], 
    [
      410, 
      482
    ]
  ], 
  "276583": [
    [
      1, 
      52
    ]
  ], 
  "276659": [
    [
      1, 
      189
    ], 
    [
      249, 
      252
    ], 
    [
      256, 
      257
    ], 
    [
      259, 
      260
    ]
  ], 
  "276655": [
    [
      1, 
      449
    ], 
    [
      495, 
      843
    ], 
    [
      895, 
      1106
    ]
  ], 
  "276584": [
    [
      1, 
      4
    ], 
    [
      6, 
      6
    ]
  ], 
  "276776": [
    [
      1, 
      962
    ], 
    [
      1082, 
      1823
    ]
  ], 
  "276775": [
    [
      1, 
      135
    ], 
    [
      162, 
      334
    ], 
    [
      364, 
      544
    ], 
    [
      577, 
      814
    ], 
    [
      852, 
      963
    ], 
    [
      1003, 
      1260
    ]
  ], 
  "276653": [
    [
      1, 
      218
    ], 
    [
      250, 
      550
    ]
  ], 
  "276361": [
    [
      1, 
      86
    ], 
    [
      117, 
      833
    ]
  ], 
  "276363": [
    [
      1, 
      123
    ], 
    [
      228, 
      271
    ], 
    [
      549, 
      596
    ], 
    [
      1329, 
      1390
    ], 
    [
      1454, 
      1482
    ]
  ], 
  "276315": [
    [
      1, 
      92
    ], 
    [
      120, 
      217
    ]
  ], 
  "276545": [
    [
      2, 
      61
    ], 
    [
      117, 
      214
    ], 
    [
      218, 
      218
    ], 
    [
      224, 
      225
    ], 
    [
      227, 
      227
    ], 
    [
      230, 
      230
    ]
  ], 
  "276794": [
    [
      1, 
      893
    ], 
    [
      895, 
      895
    ]
  ], 
  "276454": [
    [
      1, 
      528
    ], 
    [
      530, 
      535
    ], 
    [
      537, 
      543
    ], 
    [
      545, 
      552
    ], 
    [
      554, 
      556
    ], 
    [
      559, 
      561
    ], 
    [
      563, 
      565
    ]
  ], 
  "276810": [
    [
      1, 
      82
    ], 
    [
      125, 
      287
    ]
  ], 
  "276811": [
    [
      47, 
      138
    ], 
    [
      187, 
      332
    ], 
    [
      383, 
      871
    ], 
    [
      991, 
      1270
    ], 
    [
      1272, 
      1340
    ], 
    [
      1415, 
      1626
    ], 
    [
      1701, 
      2574
    ]
  ], 
  "276527": [
    [
      1, 
      214
    ]
  ], 
  "276525": [
    [
      1, 
      86
    ], 
    [
      88, 
      173
    ], 
    [
      204, 
      469
    ], 
    [
      471, 
      645
    ], 
    [
      683, 
      1265
    ], 
    [
      1360, 
      1718
    ], 
    [
      1772, 
      2491
    ], 
    [
      2559, 
      2893
    ]
  ], 
  "276528": [
    [
      4, 
      84
    ], 
    [
      168, 
      400
    ]
  ], 
  "276495": [
    [
      1, 
      268
    ]
  ], 
  "276501": [
    [
      4, 
      84
    ], 
    [
      112, 
      140
    ], 
    [
      169, 
      283
    ], 
    [
      314, 
      379
    ], 
    [
      417, 
      492
    ], 
    [
      528, 
      816
    ], 
    [
      856, 
      894
    ], 
    [
      935, 
      1015
    ], 
    [
      1099, 
      1547
    ], 
    [
      1597, 
      1695
    ], 
    [
      1748, 
      2065
    ], 
    [
      2122, 
      2236
    ], 
    [
      2355, 
      2547
    ]
  ], 
  "276502": [
    [
      2, 
      748
    ]
  ]
}